Workbook

Sheet Leia-me
C3: Guia de uso
C5: Reconstrução acadêmica da auditoria — matrícula 202062044
C6: Dados públicos e simulação sintética | sem opinião independente
C8: Campo | D8: Descrição
C9: Identificação | D9: Matrícula 202062044.
C10: Período | D10: Exercício encerrado em 31/12/2025; relatório publicado em 26/02/2026.
C11: Unidade | D11: BRL mil, salvo indicação em contrário.
C12: Escopo | D12: Base e exceções são sintéticas; apenas saldos agregados da Nota 11 foram calibrados.
C13: Planilha | D13: Contém saldos, materialidade, riscos, análises, programas, amostras, exceções e cobertura de normas.
C14: Limite | D14: Os testes computacionais usam dados sintéticos; não conclua sobre os registros reais da MDIA3.
C15: Reprodução | D15: Instale requirements.txt e execute os comandos de reprodução descritos no README.
C16: README | D16: Reúne matrícula, organização do repositório e comandos de reprodução.
C17: IA | D17: Inteligência artificial foi utilizada como apoio à elaboração, com revisão e validação integradas ao trabalho acadêmico.

Sheet Materialidade
C3: Materialidade
C5: Premissas acadêmicas ilustrativas e análise de sensibilidade
C6: BRL mil; as porcentagens são julgamentos didáticos, não percentuais mandatórios da NBC TA 320
C9: Resultado antes de IR/CSLL | D9: 708270
C10: Receita líquida | D10: 10437548
C11: Ativo total | D11: 12559343
C12: Benchmark escolhido | D12: 0.05
C13: Materialidade execução (% global) | D13: 0.5
C14: Limite trivial (% global) | D14: 0.05
C15: Materialidade global | D15: =D9*D12 -> 35413.5
C16: Materialidade para execução | D16: =D15*D13 -> 17706.75
C17: Limite trivial | D17: =D15*D14 -> 1770.675
C18: Benchmark alternativo: 0,5% receita | D18: =D10*D34 -> 52187.74
C19: Benchmark alternativo: 1% ativo | D19: =D11*D35 -> 125593.43
C20: Global / receita | D20: =D15/D10 -> 0.0033928946
C21: Global / ativo | D21: =D15/D11 -> 0.0028196937
C23: Interpretação
C24: Materialidade não é uma conta do ativo nem um corte automático por conta. O PBT foi escolhido provisoriamente por ser medida de desempenho potencialmente relevante para entidade lucrativa, mas caiu 14,0% e inclui BRL 463.419 mil de subvenção estadual. Benchmarks alternativos e a exclusão mecânica dessa linha são sensibilidades, não ajuste contábil nem escolha automática do benchmark correto.
C27: Subvenção estadual na DRE (2025) | D27: 463419
C28: PBT sem essa linha — sensibilidade | D28: =D9-D27 -> 244851
C29: Global a 5% do PBT sensível | D29: =D28*D12 -> 12242.55
C30: Execução a 50% | D30: =D29*D13 -> 6121.275
C31: Trivial a 5% da global | D31: =D29*D14 -> 612.1275
C32: Benchmark alternativo: receita | D32: =D10*D34 -> 52187.74
C33: Benchmark alternativo: ativo | D33: =D11*D35 -> 125593.43
C34: Percentual alternativo sobre receita | D34: 0.005
C35: Percentual alternativo sobre ativo | D35: 0.01
C36: Execução alternativa: 0,5% receita | D36: =D18*D13 -> 26093.87
C37: Trivial alternativo: 0,5% receita | D37: =D18*D14 -> 2609.387
C38: Execução alternativa: 1% ativo | D38: =D19*D13 -> 62796.715
C39: Trivial alternativo: 1% ativo | D39: =D19*D14 -> 6279.6715

Sheet Saldos
C3: Saldos
C5: Principais saldos publicados e composição do imobilizado
C6: BRL mil; saldos consolidados
C8: Rubrica | D8: 2025 | E8: 2024 | F8: Referência
C9: Ativo total | D9: 12559343 | E9: 12768867 | F9: Balanço consolidado
C10: Imobilizado | D10: 3570990 | E10: 3590675 | F10: Balanço consolidado/Nota 11
C11: Intangível | D11: 2416590 | E11: 2414480 | F11: Balanço consolidado/Nota 12
C12: Caixa e equivalentes | D12: 1888270 | E12: 2152587 | F12: Balanço consolidado/Nota 5
C13: Clientes — total comparável | D13: 1843604 | E13: 1670045 | F13: Balanço consolidado/Nota 6; 2024 inclui circulante + não circulante
C14: Estoques | D14: 1675464 | E14: 1687637 | F14: Balanço consolidado/Nota 7
C15: Passivo circulante | D15: 2235103 | E15: 2732737 | F15: Balanço consolidado
C16: Receita líquida | D16: 10437548 | E16: 9662833 | F16: Nota 27
C17: Resultado antes IR/CSLL | D17: 708270 | E17: 823185 | F17: Demonstração do resultado/fluxo de caixa
C18: Custo bruto imobilizado | D18: 7205695 | F18: Nota 11
C19: Depreciação acumulada | D19: 3634705 | F19: Nota 11
C23: Classe | D23: Registros sintéticos | E23: Custo bruto | F23: Depreciação acumulada | G23: Saldo líquido
C24: Edificações | D24: 3000 | E24: 1740776 | F24: 548812 | G24: 1191964
C25: Máquinas e equipamentos | D25: 210000 | E25: 3682384 | F25: 2388537 | G25: 1293847
C26: Móveis e utensílios | D26: 160000 | E26: 145342 | F26: 97227 | G26: 48115
C27: Veículos | D27: 10000 | E27: 256948 | F27: 127743 | G27: 129205
C28: Instalações | D28: 40000 | E28: 572492 | F28: 306773 | G28: 265719
C29: Imobilizações em andamento | D29: 30000 | E29: 415229 | F29: 2220 | G29: 413009
C30: Outros | D30: 47000 | E30: 392524 | F30: 163393 | G30: 229131
C31: Total | D31: =SUM(D24:D30) -> 500000 | E31: =SUM(E24:E30) -> 7205695 | F31: =SUM(F24:F30) -> 3634705 | G31: =SUM(G24:G30) -> 3570990

Sheet Seleção da conta
C3: Seleção da conta para a base
C5: Comparação de magnitude e fatores de risco dos principais saldos de ativo
C6: Saldos consolidados 2025; magnitude não é sinônimo de materialidade normativa
C8: Conta | D8: Saldo 2025 (BRL mil) | E8: % do ativo | F8: Fatores de risco | G8: Conclusão acadêmica
C9: Imobilizado | D9: =Saldos!D10 -> 3570990 | E9: =D9/Saldos!D9 -> 0.28432936 | F9: Maior linha individual de ativo; existência, direitos, baixas, depreciação, projetos em andamento e impairment. | G9: Selecionada para a base obrigatória pela maior magnitude individual entre as principais rubricas e pelos riscos inerentes.
C10: Intangível | D10: =Saldos!D11 -> 2416590 | E10: =D10/Saldos!D9 -> 0.19241373 | F10: Estimativa/impairment de goodwill e marcas; alto julgamento, apesar de saldo inferior ao imobilizado. | G10: Risco de estimativa elevado; não é a maior linha individual por saldo.
C11: Caixa e equivalentes | D11: =Saldos!D12 -> 1888270 | E11: =D11/Saldos!D9 -> 0.15034783 | F11: Existência, restrição, direitos e confirmação bancária. | G11: Saldo relevante; testes dependem de confirmações e extratos.
C12: Clientes | D12: =Saldos!D13 -> 1843604 | E12: =D12/Saldos!D9 -> 0.14679144 | F12: Existência, direitos, aging e perda esperada. | G12: Saldo relevante; expectativa analítica requer investigação.
C13: Estoques | D13: =Saldos!D14 -> 1675464 | E13: =D13/Saldos!D9 -> 0.13340379 | F13: Existência física, custo, obsolescência e valor realizável líquido. | G13: Saldo relevante; exige observação física e testes de custo.
C17: Conclusão
C18: A NBC TA 320 não determina uma rubrica “mais material” apenas pelo saldo. Para cumprir a exigência de base, o imobilizado é a escolha mais defensável entre as principais linhas individuais: é a maior por valor (BRL 3.570.990 mil; 28,43% do ativo) e possui riscos inerentes relevantes. A avaliação de risco também destaca intangível e receita, e a hierarquia pode mudar com informação interna ou necessidades específicas de usuários.

Sheet Riscos
C3: Matriz de riscos
C5: Riscos inerentes, afirmações e resposta planejada
C6: Planejamento; não equivale a procedimento executado em dados reais
C8: Área | D8: Risco | E8: Afirmações | F8: Fator | G8: Resposta planejada | H8: Limitação
C9: Receita líquida 10.437.548 | D9: Alto | E9: Ocorrência, exatidão, corte, apresentação | F9: Fraude presumida no reconhecimento; venda faturada sem transferência de controle | G9: Testar entregas de dezembro/janeiro, devoluções, contratos, lançamentos e razão | H9: Base de vendas/entrega e razão indisponíveis
C10: Imobilizado 3.570.990 | D10: Alto | E10: Existência, direitos, integridade, valoração, corte, classificação | F10: Adições/baixas, vida útil/depreciação, projetos em andamento, impairment | G10: Auxiliar ao razão, títulos, inspeção, recálculo, baixas, capex em andamento | H10: Só saldos públicos e população sintética
C11: Intangível 2.416.590 | D11: Alto | E11: Existência, direitos, valoração, classificação, divulgação | F11: Goodwill/marcas sem amortização e fluxo descontado | G11: Testar CGUs, budgets, forecasts, taxa 13,04%, crescimento terminal 3,9%, sensibilidade | H11: Modelo detalhado ausente
C12: Clientes 1.843.604; ECL 60.051 | D12: Alto/moderado | E12: Existência, direitos, valoração | F12: Aging, exposição vencida, premissas ECL | G12: Confirmações, recebimentos subsequentes, recalcular aging e modelo | H12: Auxiliar e confirmações ausentes
C13: Estoques 1.675.464; perda 31.481 | D13: Alto | E13: Existência, integridade, valoração, corte | F13: Contagem, custo médio, obsolescência/VRL | G13: Contagem observada, teste de custos, venda subsequente | H13: Sem contagem e fichas de custo
C14: Provisões 200.718; contingências possíveis 2.307.733 | D14: Alto qualitativo | E14: Integridade, mensuração, apresentação | F14: Completude e classificação probabilidade | G14: Carta jurídica, autos, atualização e cálculo | H14: Sem carta/autos; contingência possível não é passivo reconhecido
C15: Caixa 1.888.270; derivativos | D15: Moderado/alto | E15: Existência, direitos, valor justo, classificação | F15: Restrição, contraparte, hedge | G15: Confirmações, extratos, recálculo e documentação hedge | H15: Sem confirmações
C16: Dívida 1.419.965; arrendamentos 322.005 | D16: Moderado | E16: Integridade, obrigação, valoração, classificação | F16: Vencimentos, covenant, taxa, juros | G16: Confirmações, contratos, recálculo, busca de passivo | H16: Sem contratos completos

Sheet Amostra
C3: Amostragem
C5: Desenho didático sobre a população sintética
C6: Sem extrapolação para MDIA3; AAS de atributo não é amostra monetária
C8: Parâmetro | D8: Valor | E8: Comentário
C9: População | D9: 500000 | E9: Itens sintéticos com IDs únicos; não são cadastro da companhia
C10: Unidade | D10: 1 linha = 1 item fictício | E10: Não equivale a unidade real de cadastro
C11: AAS descritiva | D11: 384 | E11: Sem reposição; seed 5302025; objetivo: presença de ID, classe e 3 campos monetários; 0/384 ausentes
C12: Seleção dirigida | D12: 25 maiores saldos + censo das flags | E12: Não probabilística; não projetável
C13: Amostra combinada | D13: 441 | E13: AAS mais seleções dirigidas, IDs deduplicados
C14: MUS sistemática | D14: 606 unidades monetárias; 603 IDs únicos | E14: Distorção tolerável proxy = PM BRL 17.706,75 mil; fator 3,0; erro esperado zero
C15: Intervalo MUS | D15: =Saldos!D10/606 -> 5892.7228 | E15: Início aleatório reproduzível; consultar amostra_monetaria_MUS.csv
C16: Projeção pontual MUS | D16: BRL 41.785,446 mil | E16: BRL 30.000 mil em três itens de certeza + dois itens × intervalo; estimativa pontual didática, não limite superior nem projeção para MDIA3.
C17: Detalhe da projeção | D17: pt530_detalhe_projecao_mus.csv | E17: Cinco baixas sintéticas selecionadas; pontos MUS, saldo, certeza, tainting e parcela projetada.
C18: Flags do cenário | D18: 37 exceções | E18: 5 baixas; 12 projetos; 12 etiquetas; 8 não localizados
C19: Limitação | D19: Desenho didático em base sintética | E19: Projeção e atributos não sustentam opinião; recalcular com população real em auditoria

Sheet Exceções
C3: Distorções e exceções
C5: Separar cenário simulado de achados reais
C6: Nenhum item desta planilha é ocorrência real da companhia
C8: Classe | D8: Qtd | E8: Exposição potencial (BRL mil) | F8: Comparação | G8: Conclusão/limite
C9: Baixas não registradas | D9: 5 | E9: 39000 | F9: 1,10× global; 2,20× execução; 5,51% PBT | G9: Factual apenas no cenário; custo 48.500, depreciação 9.500, líquido 39.000. Correção suposta sem produto da alienação reduziria o resultado antes de tributos em 39.000.
C10: Itens em andamento possivelmente disponíveis | D10: 12 | F10: Não quantificado | G10: Inconsistência sintética de dados; efeito de depreciação depende de data real, custo, vida útil e valor residual.
C11: Etiqueta ausente | D11: 12 | F11: Não quantificado | G11: Controle/rastreabilidade; não é automaticamente distorção contábil.
C12: Não localizado simulado | D12: 8 | E12: 3.848 | F12: Equivale a BRL 3.848 correntes | G12: Resultado fabricado; não é inspeção real; sem evidência para ajuste.
C13: Distorções reais identificadas | D13: 0 | E13: 0 | F13: Não testadas | G13: Nenhuma distorção real pode ser declarada sem evidência dos registros da companhia.

Sheet Analíticos
C3: Procedimentos analíticos
C5: Expectativas, limiar de investigação e resultados reproduzíveis
C6: BRL mil; expectativas didáticas baseadas em dados públicos agregados
C8: Analítico | D8: Saldo 2025 | E8: Base/expectativa 2024 | F8: Diferença/variação | G8: Limiar de triagem | H8: Investigação/resposta
C9: Clientes: expectativa proporcional à receita | D9: =Saldos!D13 -> 1843604 | E9: =Saldos!E13*(Saldos!D16/Saldos!E16) -> 1803940.4 | F9: =D9-E9 -> 39663.598 | G9: =Materialidade!D16 -> 17706.75 | H9: 2024 total comparável BRL 1.670.045; expectativa 2025 BRL 1.803.940,402; diferença BRL 39.663,598 (~2,24x PM). Investigar mix, prazo, aging, moeda, concentração, recebimentos e ECL; não é erro identificado.
C10: Receita líquida: variação anual | D10: =Saldos!D16 -> 10437548 | E10: =Saldos!E16 -> 9662833 | F10: =Saldos!D16/Saldos!E16-1 -> 0.080174727 | G10: =Materialidade!D16 -> 17706.75 | H10: Aumento percentual: decompor por mês/produto/preço/volume e testar corte; diferença percentual não é erro monetário.
C11: Resultado antes de IR/CSLL: variação anual | D11: =Saldos!D17 -> 708270 | E11: =Saldos!E17 -> 823185 | F11: =Saldos!D17/Saldos!E17-1 -> -0.13959802 | G11: =Materialidade!D16 -> 17706.75 | H11: Queda de resultado superior à mudança de receita; testar margem, financeiro, subvenções e itens não recorrentes.
C12: Imobilizado líquido: variação anual | D12: =Saldos!D10 -> 3570990 | E12: =Saldos!E10 -> 3590675 | F12: =Saldos!D10/Saldos!E10-1 -> -0.0054822561 | G12: =Materialidade!D16 -> 17706.75 | H12: Conciliar adições, depreciação, baixas, transferências, impairment e direitos de uso.

Sheet Programa
C3: Programas de auditoria
C5: Procedimentos por afirmação, natureza, época e extensão
C6: Planejados para cenário de auditoria; execução real não ocorreu
C8: PT/área | D8: Risco/afirmação | E8: Procedimento | F8: Natureza | G8: Época | H8: Extensão/amostra | I8: Execução/limite
C9: PT240/330 | D9: Receita: ocorrência, exatidão, corte; fraude presumida | E9: Teste substantivo de notas, pedidos, prova de entrega/aceite, devoluções subsequentes e lançamentos manuais; conciliar faturamento ao razão. | F9: Detalhe + analítico | G9: Dezembro 2025 e janeiro/fevereiro 2026; incluir seleção antes/depois do corte. | H9: Estratificar por mês/produto e risco; tamanho após tolerância e risco definidos. | I9: Não executado: não há base de vendas nem documentos.
C10: PT315/330 | D10: SAP S/4HANA e dados de reporte: integridade, exatidão, acesso | E10: Entender migração Simplifique concluída em 2024, integração declarada de 47 sistemas; testar controles gerais de TI, interfaces, acessos e lançamentos manuais. | F10: Walkthrough + testes de controles + substantivo | G10: Migração 2024 e operação 2025; controles ao longo do exercício. | H10: Selecionar interfaces críticas, usuários privilegiados, mudanças e journals por risco. | I10: Risco identificado em divulgação; sem acesso a SAP, logs ou ITGC.
C11: PT530 | D11: Imobilizado: existência, valor e baixas | E11: Seleção MUS sistemática da população sintética; inspeção bidirecional apenas se ativos/evidências reais forem disponibilizados. | F11: Amostragem monetária + detalhe | G11: Data-base 31/12/2025; altas e baixas no exercício. | H11: 606 unidades monetárias; início aleatório e intervalo no script/CSV; PM usada como proxy de distorção tolerável. | I11: Executado somente no conjunto sintético; sem inferência para a MDIA3.
C12: PT330 | D12: Imobilizado: direitos, mensuração e depreciação | E12: Vouching de adições a nota/contrato; recálculo de depreciação; exame de baixas, alienações e transferência de projetos. | F12: Detalhe | G12: Amostra de adições/baixas de 2025 e itens de maior valor. | H12: Itens selecionados pelo MUS e itens de alto risco; cobertura orientada por afirmação. | I12: Não executado em registros da empresa; classe de direito de uso não separada na base sintética.
C13: PT501 | D13: Estoques: existência e valor realizável líquido | E13: Acompanhar inventário físico; testar contagens, custo médio, obsolescência e venda subsequente. | F13: Observação + detalhe | G13: Data do inventário e testes de corte no encerramento. | H13: Locais/materialidade por local; itens de alto valor e itens selecionados. | I13: Sem contagem, fichas de custo ou vendas posteriores granulares.
C14: PT505/330 | D14: Disponibilidades: existência, direitos, restrições e classificação | E14: Confirmar bancos sob controle do auditor; reconciliar extratos, aplicações, restrições e corte. | F14: Confirmação externa + detalhe | G14: Próximo a 31/12/2025 e conciliações posteriores. | H14: População bancária real e todas as contas relevantes; valores/contatos ainda não disponíveis. | I14: Somente modelo de confirmação; sem população, envio, resposta ou teste.
C15: PT505/330 | D15: Passivos financeiros: completude, obrigação, mensuração e covenant | E15: Confirmar financiadores; inspecionar contratos, juros, vencimentos, garantias e covenants; recalcular saldos. | F15: Confirmação externa + detalhe | G15: Data-base e pagamentos posteriores. | H15: Todos os financiadores relevantes e contratos; seleção após obter razão/contratos. | I15: Sem confirmação, contratos completos ou razão.
C16: PT330/550 | D16: Derivativos: existência, direitos, valor justo e divulgação | E16: Confirmar termos com contrapartes; recalcular valor justo e avaliar designação/efetividade de hedge. | F16: Confirmação externa + recálculo | G16: Posições em 31/12/2025 e transações subsequentes. | H16: Censo das posições relevantes; suporte/contratos ausentes. | I16: Somente divulgações agregadas; sem confirmação ou recálculo independente.
C17: PT250/501 | D17: Provisões/contingências: completude e mensuração | E17: Solicitar carta jurídica, processos, cálculo de provisões e avaliação de probabilidade; verificar CPC 25 e divulgação. | F17: Confirmação jurídica + inspeção | G17: Até a data do relatório. | H17: Censo de processos materiais; população jurídica não disponível. | I17: Sem carta, autos, assessoria jurídica ou razão auxiliar.
C18: PT505 | D18: Clientes: existência/direitos e perda esperada | E18: Confirmação positiva de saldos, recebimentos subsequentes, aging e recálculo da ECL. | F18: Confirmação externa + detalhe | G18: Confirmações próximas a 31/12/2025; alternativas após não respostas. | H18: Estratificar por saldo, atraso, disputa e risco; amostra definida após população real. | I18: Minuta apenas; nenhuma confirmação foi enviada.
C19: PT540 | D19: Goodwill e marcas: valoração | E19: Testar CGUs, modelo DCF, dados, projeções, taxa de desconto, crescimento terminal, sensitividade e viés. | F19: Teste de estimativa + analítico | G19: Teste anual e orçamento aprovado para 2026–2030. | H19: Cobertura de todas as CGUs relevantes; cenário de taxa/growth não substitui reexecução do modelo. | I19: Somente sensibilidade relativa calculada; modelo/folga ausentes.
... C22: PT600 | D22: Consolidação e componentes: integridade/valoração | E22: Validar perímetro, balancetes, eliminações, políticas, câmbio e trabalho de auditores de componentes; CPC 15/36. | F22: Consolidação + revisão de componentes | G22: Fechamento anual e saldos comparativos. | H22: Cobrir componentes significativos e riscos por componente; extensão após materialidade de grupo/componente. | I22: Mapeamento só documental; sem balancetes e papéis dos componentes.

Sheet Normas
C3: Normas
C5: Versões, vigência e status da evidência
C6: NBC TA 200–600: escopo principal; normas 700+ apenas como referência suplementar ao modelo
C8: PT | D8: Norma/versão | E8: Vigência/base | F8: Objeto/procedimento | G8: Status/limite
C9: EC | D9: NBC TA Estrutura Conceitual | E9: Não se aplica — Estrutura Conceitual | F9: Define objeto demonstrações públicas, critérios NBC TG/CPC, partes, evidência e nível | G9: Análise documental
C10: PT200 | D10: NBC TA 200 (R1) | E10: Períodos iniciados em ou após 01/01/2010 — aplicável a 2025 | F10: Ética, independência, ceticismo e limites | G10: Planejado/documentado, não é auditoria profissional
C11: PT210 | D11: NBC TA 210 (R1) | E11: Períodos iniciados em ou após 01/01/2010 — aplicável a 2025 | F11: Objetivo, alcance, responsabilidades, acesso e precondições | G11: Minuta acadêmica não assinada/não enviada
C12: PT220 | D12: NBC TA 220 (R3) | E12: Períodos iniciados em ou após 01/01/2023 — aplicável a 2025 | F12: Direção, supervisão, revisão, recursos, consulta e independência; divulgação de serviços da KPMG e pré-aprovação pelo Comitê de Auditoria | G12: Análise documental; sem equipe/revisor independente ou avaliação própria de independência
C13: PT230 | D13: NBC TA 230 (R1) | E13: Períodos iniciados em ou após 01/01/2010 — aplicável a 2025 | F13: Índice, referência cruzada e versão 2.0; sementes e trilha de reprodução em README/código. | G13: Arquivo acadêmico versionado para esta entrega; retenção profissional e histórico remoto dependem da ação manual no GitHub.
C14: PT240 | D14: NBC TA 240 (R1) | E14: Períodos iniciados em ou após 01/01/2010 — aplicável a 2025 | F14: Reconhecimento de receitas, override, lançamentos e estimativas | G14: Riscos planejados; NBC TA 240 (R2) foi publicada em 2026 para períodos iniciados a partir de 01/01/2027; não aplicada a 2025.
C15: PT250 | D15: NBC TA 250 | E15: Períodos iniciados em ou após 31/12/2018 — aplicável a 2025 | F15: Provisões, subvenções estaduais e obrigações legais; avaliar CPC 07 (R1) e CPC 25 | G15: Planejado/documental; sem processos, parecer legal ou prova de cumprimento
C16: PT260 | D16: NBC TA 260 (R2) | E16: Períodos findos em ou após 31/12/2016 — aplicável a 2025 | F16: Plano de comunicação sobre estratégia, época, riscos, independência, limitações e achados; considerar divulgação pública de outros serviços. | G16: Minuta não enviada. Estatuto Social consta do inventário; a análise de governança limita-se às divulgações das DFs.
C17: PT265 | D17: NBC TA 265 | E17: Períodos iniciados em ou após 01/01/2010 — aplicável a 2025 | F17: Condição, critério, causa, efeito, recomendação e status de cada cenário | G17: Exceções plantadas na base
C18: PT300 | D18: NBC TA 300 (R1) | E18: Períodos iniciados em ou após 01/01/2010 — aplicável a 2025 | F18: Estratégia, riscos, cronograma e programas detalhados por natureza, época e extensão na aba Programa | G18: Planejamento acadêmico; ciclos reais não foram executados
C19: PT315 | D19: NBC TA 315 (R2) | E19: Períodos iniciados em ou após 01/01/2022 — aplicável a 2025 | F19: Matriz por afirmação; inclui contexto SAP/Simplifique, mas a classificação de risco significativo é limitada à presunção de fraude no reconhecimento de receita; alta prioridade não significa automaticamente risco significativo. | G19: Análise documental; sem registros, walkthrough, avaliação de desenho/implementação/eficácia, logs, ITGC ou teste de TI.
... C60: CPC 09 | D60: CPC 09 (R1) / NBC TG 09 (R1) | E60: NBC TG 09 (R1): em vigor desde 01/03/2024, aplicável a exercícios iniciados em ou após 01/01/2024; aplicável a 2025. | F60: Recalcular a formação e a distribuição do valor adicionado; conferir subtotais e apresentação da DVA. | G60: Subtotais recalculados a partir dos valores divulgados; sem schedule completo linha a linha ou razão. Não sustenta conclusão sobre apresentação/classificação.
